README.md
setup.py
cbkutils/__init__.py
cbkutils/constants.py
cbkutils/cursor.py
cbkutils/log.py
cbkutils/settings.py
cbkutils/spinner.py
cbkutils/status.py
cbkutils/utils.py
cbkutils.egg-info/PKG-INFO
cbkutils.egg-info/SOURCES.txt
cbkutils.egg-info/dependency_links.txt
cbkutils.egg-info/not-zip-safe
cbkutils.egg-info/requires.txt
cbkutils.egg-info/top_level.txt
cbkutils/backports/__init__.py
cbkutils/backports/shutil_get_terminal_size/__init__.py
cbkutils/backports/shutil_get_terminal_size/get_terminal_size.py