Metadata-Version: 1.0
Name: cbkutils
Version: 1.0
Summary: Simple helpers
Home-page: http://github.com/cidrblock/cbkutils
Author: Bradley A. Thornton
Author-email: brad@thethorntons.net
License: MIT
Platform: UNKNOWN
